{
  "mainTable": [
    {
      "name": "LA FRANCE REVIENT ! AVEC JORDAN BARDELLA ET MARINE LE PEN",
      "code": "LRN",
      "count": 322,
      "percentage1": 13.14,
      "percentage2": 23.02
    },
    {
      "name": "RÉVEILLER L'EUROPE",
      "code": "LUG",
      "count": 283,
      "percentage1": 11.55,
      "percentage2": 20.23
    },
    {
      "name": "BESOIN D'EUROPE",
      "code": "LENS",
      "count": 215,
      "percentage1": 8.78,
      "percentage2": 15.37
    },
    {
      "name": "LA FRANCE INSOUMISE - UNION POPULAIRE",
      "code": "LFI",
      "count": 141,
      "percentage1": 5.76,
      "percentage2": 10.08
    },
    {
      "name": "EUROPE ÉCOLOGIE",
      "code": "LVEC",
      "count": 120,
      "percentage1": 4.9,
      "percentage2": 8.58
    },
    {
      "name": "LA DROITE POUR FAIRE ENTENDRE LA VOIX DE LA FRANCE EN EUROPE",
      "code": "LLR",
      "count": 89,
      "percentage1": 3.63,
      "percentage2": 6.36
    },
    {
      "name": "PARTI ANIMALISTE - LES ANIMAUX COMPTENT, VOTRE VOIX AUSSI",
      "code": "LDIV",
      "count": 40,
      "percentage1": 1.63,
      "percentage2": 2.86
    },
    {
      "name": "GAUCHE UNIE POUR LE MONDE DU TRAVAIL SOUTENUE PAR FABIEN ROUSSEL",
      "code": "LCOM",
      "count": 39,
      "percentage1": 1.59,
      "percentage2": 2.79
    },
    {
      "name": "LA FRANCE FIERE, MENEE PAR MARION MARECHAL ET SOUTENUE PAR ÉRIC ZEMMOUR",
      "code": "LREC",
      "count": 38,
      "percentage1": 1.55,
      "percentage2": 2.72
    },
    {
      "name": "ÉCOLOGIE AU CENTRE",
      "code": "LECO",
      "count": 32,
      "percentage1": 1.31,
      "percentage2": 2.29
    },
    {
      "name": "ALLIANCE RURALE",
      "code": "LDVD",
      "count": 32,
      "percentage1": 1.31,
      "percentage2": 2.29
    },
    {
      "name": "LUTTE OUVRIERE - LE CAMP DES TRAVAILLEURS",
      "code": "LEXG",
      "count": 10,
      "percentage1": 0.41,
      "percentage2": 0.71
    },
    {
      "name": "ECOLOGIE POSITIVE ET TERRITOIRES",
      "code": "LECO",
      "count": 8,
      "percentage1": 0.33,
      "percentage2": 0.57
    },
    {
      "name": "L'EUROPE CA SUFFIT !",
      "code": "LEXD",
      "count": 7,
      "percentage1": 0.29,
      "percentage2": 0.5
    },
    {
      "name": "EUROPE TERRITOIRES ÉCOLOGIE",
      "code": "LDVG",
      "count": 6,
      "percentage1": 0.24,
      "percentage2": 0.43
    },
    {
      "name": "LISTE ASSELINEAU-FREXIT, POUR LE POUVOIR D'ACHAT ET POUR LA PAIX",
      "code": "LDIV",
      "count": 6,
      "percentage1": 0.24,
      "percentage2": 0.43
    },
    {
      "name": "POUR UN MONDE SANS FRONTIERES NI PATRONS, URGENCE REVOLUTION !",
      "code": "LEXG",
      "count": 5,
      "percentage1": 0.2,
      "percentage2": 0.36
    },
    {
      "name": "ÉQUINOXE : ÉCOLOGIE PRATIQUE ET RENOUVEAU DÉMOCRATIQUE",
      "code": "LECO",
      "count": 3,
      "percentage1": 0.12,
      "percentage2": 0.21
    },
    {
      "name": "CHANGER L'EUROPE",
      "code": "LDVG",
      "count": 2,
      "percentage1": 0.08,
      "percentage2": 0.14
    },
    {
      "name": "NOUS LE PEUPLE",
      "code": "LDIV",
      "count": 1,
      "percentage1": 0.04,
      "percentage2": 0.07
    },
    {
      "name": "LIBERTÉ DÉMOCRATIQUE FRANÇAISE",
      "code": "LDIV",
      "count": 0,
      "percentage1": 0,
      "percentage2": 0
    },
    {
      "name": "ESPERANTO LANGUE COMMUNE",
      "code": "LDIV",
      "count": 0,
      "percentage1": 0,
      "percentage2": 0
    },
    {
      "name": "DEMOCRATIE REPRESENTATIVE",
      "code": "LDIV",
      "count": 0,
      "percentage1": 0,
      "percentage2": 0
    },
    {
      "name": "DEFENDRE LES ENFANTS",
      "code": "LDIV",
      "count": 0,
      "percentage1": 0,
      "percentage2": 0
    },
    {
      "name": "LA RUCHE CITOYENNE",
      "code": "LDIV",
      "count": 0,
      "percentage1": 0,
      "percentage2": 0
    },
    {
      "name": "FRANCE LIBRE",
      "code": "LDIV",
      "count": 0,
      "percentage1": 0,
      "percentage2": 0
    },
    {
      "name": "NON À L'UE ET À L'OTAN, COMMUNISTES POUR LA PAIX ET LE PROGRÈS SOCIAL",
      "code": "LEXG",
      "count": 0,
      "percentage1": 0,
      "percentage2": 0
    },
    {
      "name": "FORTERESSE EUROPE - LISTE D'UNITE NATIONALISTE",
      "code": "LEXD",
      "count": 0,
      "percentage1": 0,
      "percentage2": 0
    },
    {
      "name": "NON ! PRENONS-NOUS EN MAINS",
      "code": "LDIV",
      "count": 0,
      "percentage1": 0,
      "percentage2": 0
    },
    {
      "name": "\"POUR LE PAIN, LA PAIX, LA LIBERTÉ !\" PRÉSENTÉE PAR LE PARTI DES TRAVAILLEURS",
      "code": "LEXG",
      "count": 0,
      "percentage1": 0,
      "percentage2": 0
    },
    {
      "name": "POUR UNE AUTRE EUROPE",
      "code": "LDIV",
      "count": 0,
      "percentage1": 0,
      "percentage2": 0
    },
    {
      "name": "PAIX ET DECROISSANCE",
      "code": "LEXG",
      "count": 0,
      "percentage1": 0,
      "percentage2": 0
    },
    {
      "name": "PACE - PARTI DES CITOYENS EUROPÉENS, POUR L'ARMÉE EUROPÉENNE, POUR L'EUROPE SOCIALE , POUR LA PLANÈTE !",
      "code": "LDIV",
      "count": 0,
      "percentage1": 0,
      "percentage2": 0
    },
    {
      "name": "PARTI PIRATE",
      "code": "LDIV",
      "count": 0,
      "percentage1": 0,
      "percentage2": 0
    },
    {
      "name": "PARTI REVOLUTIONNAIRE COMMUNISTES",
      "code": "LEXG",
      "count": 0,
      "percentage1": 0,
      "percentage2": 0
    },
    {
      "name": "FREE PALESTINE",
      "code": "LDIV",
      "count": 0,
      "percentage1": 0,
      "percentage2": 0
    },
    {
      "name": "POUR UNE DEMOCRATIE REELLE : DECIDONS NOUS-MEMES !",
      "code": "LDIV",
      "count": 0,
      "percentage1": 0,
      "percentage2": 0
    },
    {
      "name": "POUR UNE HUMANITE SOUVERAINE",
      "code": "LDIV",
      "count": 0,
      "percentage1": 0,
      "percentage2": 0
    }
  ],
  "summaryTable": {
    "Inscrits": 2,
    "Abstentions": 998,
    "Votants": 1,
    "Blancs": 29,
    "Nuls": 24,
    "Exprimés": 1
  },
  "commune": {
    "TYPECOM": "COM",
    "COM": "35033",
    "REG": "53",
    "DEP": "35",
    "CTCD": "35D",
    "ARR": "352",
    "TNCC": "0",
    "NCC": "BOURG DES COMPTES",
    "NCCENR": "Bourg-des-Comptes",
    "LIBELLE": "Bourg-des-Comptes",
    "CAN": "3511",
    "COMPARENT": null
  }
}